spVIPES/__init__.py
spVIPES/data/__init__.py
spVIPES/data/_constants.py
spVIPES/data/_manager.py
spVIPES/data/_multi_datasplitter.py
spVIPES/data/_utils.py
spVIPES/data/prepare_adatas.py
spVIPES/data/fields/__init__.py
spVIPES/data/fields/_base_field.py
spVIPES/dataloaders/__init__.py
spVIPES/dataloaders/_ann_dataloader.py
spVIPES/dataloaders/_concat_dataloader.py
spVIPES/model/__init__.py
spVIPES/model/spvipes.py
spVIPES/model/base/__init__py
spVIPES/model/base/training_mixin.py
spVIPES/module/__init__.py
spVIPES/module/spVIPESmodule.py
spVIPES/module/utils.py
spVIPES/nn/__init__.py
spVIPES/nn/networks.py
spVIPES/nn/utils.py
spvipes-0.3.0.dist-info/METADATA
spvipes-0.3.0.dist-info/WHEEL
spvipes-0.3.0.dist-info/licenses/LICENSE
spvipes-0.3.0.dist-info/RECORD
