Metadata-Version: 2.4
Name: spVIPES
Version: 0.3.0
Summary: Shared-private Variational Inference with Product of Experts and Supervision
Project-URL: Documentation, https://spVIPES.readthedocs.io/
Project-URL: Source, https://github.com/nrclaudio/spVIPES
Project-URL: Home-page, https://github.com/nrclaudio/spVIPES
Author: Claudio Novella Rausell
Maintainer-email: Claudio Novella Rausell <c.novella_rausell@lumc.nl>
License: BSD 3-Clause License
License-File: LICENSE
Requires-Python: >=3.9
Requires-Dist: anndata==0.10.8
Requires-Dist: numpy>=1.21.0
Requires-Dist: pandas>=1.5.0
Requires-Dist: scanpy>=1.9.1
Requires-Dist: scvi-tools==0.20.0
Requires-Dist: session-info
Requires-Dist: torch
Provides-Extra: dev
Requires-Dist: pre-commit; extra == 'dev'
Requires-Dist: twine>=4.0.2; extra == 'dev'
Provides-Extra: doc
Requires-Dist: docutils!=0.18.*,!=0.19.*,>=0.8; extra == 'doc'
Requires-Dist: ipykernel; extra == 'doc'
Requires-Dist: ipython; extra == 'doc'
Requires-Dist: myst-nb; extra == 'doc'
Requires-Dist: sphinx-autodoc-typehints; extra == 'doc'
Requires-Dist: sphinx-book-theme>=1.0.0; extra == 'doc'
Requires-Dist: sphinx-copybutton; extra == 'doc'
Requires-Dist: sphinx>=4; extra == 'doc'
Requires-Dist: sphinxcontrib-bibtex>=1.0.0; extra == 'doc'
Requires-Dist: sphinxext-opengraph; extra == 'doc'
Provides-Extra: test
Requires-Dist: pytest; extra == 'test'
Requires-Dist: pytest-cov; extra == 'test'
